setup.cfg
setup.py
beanstream/__init__.py
beanstream/billing.py
beanstream/compat.py
beanstream/errors.py
beanstream/gateway.py
beanstream/location_codes.py
beanstream/notifications.py
beanstream/payment_profiles.py
beanstream/process_transaction.py
beanstream/recurring_billing.py
beanstream/reports.py
beanstream/response_codes.py
beanstream/transaction.py
beanstream/utilities.py
beanstream.egg-info/PKG-INFO
beanstream.egg-info/SOURCES.txt
beanstream.egg-info/dependency_links.txt
beanstream.egg-info/top_level.txt